HexDisplay.v
module HexDisplay (
    input [3:0] in,
    output reg [6:0] out
);
    always @(*) begin
        case (in)
            4'h0: out = 7'b1000000;
            4'h1: out = 7'b1111001;
            4'h2: out = 7'b0100100;
            4'h3: out = 7'b0110000;
            4'h4: out = 7'b0011001;
            4'h5: out = 7'b0010010;
            4'h6: out = 7'b0000010;
            4'h7: out = 7'b1111000;
            4'h8: out = 7'b0000000;
            4'h9: out = 7'b0010000;
            4'hA: out = 7'b0001000;
            4'hB: out = 7'b0000011;
            4'hC: out = 7'b1000110;
            4'hD: out = 7'b0100001;
            4'hE: out = 7'b0000110;
            4'hF: out = 7'b0001110;
            default: out = 7'b1111111;
        endcase
    end
endmodule

Datapath.v
module Datapath (
    input clk,
    input reset,
    input regwrite,
    input alusrc,
    input memread,
    input memwrite,
    input memtoreg,
    input branch,
    input jump,
    input [2:0] aluop,

    input [15:0] data_in,         // External data input for memory (optional)
    input [2:0] reg_select,       // For HEX display
    output [15:0] reg_out,        // Value of selected register
    output [3:0] opcode,          // Output to FSM
    output zero                  // From ALU
);

    // Program Counter
    reg [7:0] pc;
    wire [15:0] instruction;
    wire [15:0] alu_result;
    wire [15:0] reg_data1, reg_data2;
    wire [15:0] write_data;
    wire [15:0] mem_data;
    wire [15:0] alu_input2;
    wire [2:0] rs, rt, rd;

    // Instruction ROM (you can replace this with RAM for more flexibility)
    reg [15:0] rom [0:255];
    initial begin
        // Example: add r1, r2, r3 → opcode = 0000, rs=r2, rt=r3, rd=r1
        rom[0] = 16'b0000_010_011_001_000;  // add r1 = r2 + r3
        rom[1] = 16'b1000_000_001_000_000;  // load r0, mem[r1]
        // Add more instructions as needed
    end
    assign instruction = rom[pc];
    assign opcode = instruction[15:12];
    assign rs = instruction[11:9];
    assign rt = instruction[8:6];
    assign rd = instruction[5:3];
    
    // Program Counter Logic
    always @(posedge clk or posedge reset) begin
        if (reset)
            pc <= 0;
        else if (jump)
            pc <= instruction[7:0];     // For jmp instruction
        else if (branch && zero)
            pc <= pc + instruction[7:0]; // Relative branch
        else
            pc <= pc + 1;
	end			
				
	 reg [15:0] instr_mem [0:31];
	 initial begin
	 	  instr_mem[0] = 16'b1000001000000000; // load r1, addr 0
		  instr_mem[1] = 16'b1000010000000001; // load r2, addr 1
	 	  instr_mem[2] = 16'b0000011001010000; // add  r3 = r1 + r2
		  instr_mem[3] = 16'b1001011000000010; // store r3 → addr 2
		  instr_mem[4] = 16'b1010001010000000; // beq r1, r2, next
		  instr_mem[5] = 16'b1011000000000000; // jmp to 0
		  instr_mem[6] = 16'b0100100011000000; // mov r4 = r3
	 end
	 
	 // Data Memory Initialization
	 reg [15:0] data_mem [0:31];
	 initial begin
		  data_mem[0] = 16'd5;   // mem[0] = 5
		  data_mem[1] = 16'd3;   // mem[1] = 3
		  data_mem[2] = 16'd0;   // result goes here
	 end
endmodule

ControlFSM.v
module ControlFSM(
    input clk,
    input reset,
    input [3:0] opcode,
    input zero,

    output reg regwrite,
    output reg alusrc,
    output reg memread,
    output reg memwrite,
    output reg memtoreg,
    output reg branch,
    output reg jump,
    output reg [2:0] aluop
);

    parameter IFETCH = 3'd0, DECODE = 3'd1, EXECUTE = 3'd2, 
             MEM = 3'd3, WB = 3'd4, BRANCH = 3'd5, JUMP = 3'd6;

    reg [2:0] current_state, next_state;

    // Instruction opcodes
    localparam [3:0]
        OP_ADD   = 4'b0000,
        OP_SUB   = 4'b0001,
        OP_AND   = 4'b0010,
        OP_OR    = 4'b0011,
        OP_MOV   = 4'b0100,
        OP_LOAD  = 4'b1000,
        OP_STORE = 4'b1001,
        OP_BEQ   = 4'b1100,
        OP_JMP   = 4'b1101;

    // ALU Operations
    localparam [2:0]
        ALU_ADD = 3'b000,
        ALU_SUB = 3'b001,
        ALU_AND = 3'b010,
        ALU_OR  = 3'b011,
        ALU_PASS = 3'b100;

    // FSM state register
    always @(posedge clk or posedge reset) begin
        if (reset)
            current_state <= IFETCH;
        else
            current_state <= next_state;
    end

    // State transitions
    always @(*) begin
        case (current_state)
            IFETCH:  next_state = DECODE;
            DECODE: begin
                case (opcode)
                    OP_ADD, OP_SUB, OP_AND, OP_OR, OP_MOV: next_state = EXECUTE;
                    OP_LOAD, OP_STORE:                     next_state = MEM;
                    OP_BEQ:                                next_state = BRANCH;
                    OP_JMP:                                next_state = JUMP;
                    default:                               next_state = IFETCH;
                endcase
            end
            EXECUTE: next_state = WB;
            MEM:     next_state = WB;
            WB:      next_state = IFETCH;
            BRANCH:  next_state = IFETCH;
            JUMP:    next_state = IFETCH;
            default: next_state = IFETCH;
        endcase
    end

    // Control outputs
    always @(*) begin
        // Default all signals
        regwrite   = 0;
        alusrc     = 0;
        memread    = 0;
        memwrite   = 0;
        memtoreg   = 0;
        branch     = 0;
        jump       = 0;
        aluop      = ALU_ADD;

        case (current_state)
            EXECUTE: begin
                regwrite = 1;
                case (opcode)
                    OP_ADD: aluop = ALU_ADD;
                    OP_SUB: aluop = ALU_SUB;
                    OP_AND: aluop = ALU_AND;
                    OP_OR:  aluop = ALU_OR;
                    OP_MOV: aluop = ALU_PASS;
                endcase
            end
            MEM: begin
                alusrc = 1;
                if (opcode == OP_LOAD) begin
                    memread = 1;
                end else if (opcode == OP_STORE) begin
                    memwrite = 1;
                    regwrite = 0;
                end
            end
            WB: begin
                if (opcode == OP_LOAD) begin
                    regwrite = 1;
                    memtoreg = 1;
                end
            end
            BRANCH: begin
                if (zero)
                    branch = 1;
                aluop = ALU_SUB;
            end
            JUMP: begin
                jump = 1;
            end
        endcase
    end

endmodule

Processor.v
module Processor (
    input clk,
    input reset,
    input [2:0] SW,          // Register select input
    output [6:0] HEX0        // 7-segment output
);
    wire regwrite, alusrc, memread, memwrite, memtoreg, branch, jump;
    wire [2:0] aluop;
    wire [3:0] opcode;
    wire [15:0] reg_out;
    wire zero;

    // FSM instance
    ControlFSM control (
        .clk(clk),
        .reset(reset),
        .opcode(opcode),
        .zero(zero),
        .regwrite(regwrite),
        .alusrc(alusrc),
        .memread(memread),
        .memwrite(memwrite),
        .memtoreg(memtoreg),
        .branch(branch),
        .jump(jump),
        .aluop(aluop)
    );

    // Datapath instance
    Datapath datapath (
        .clk(clk),
        .reset(reset),
        .regwrite(regwrite),
        .alusrc(alusrc),
        .memread(memread),
        .memwrite(memwrite),
        .memtoreg(memtoreg),
        .branch(branch),
        .jump(jump),
        .aluop(aluop),
        .data_in(16'b0),          // Optional external data in
        .reg_select(SW),
        .reg_out(reg_out),
        .opcode(opcode),
        .zero(zero)
    );

    // HEX Display (only lower 4 bits shown)
    HexDisplay display (
        .in(reg_out[3:0]),
        .out(HEX0)
    );
endmodule

Processor_TB.v
`timescale 1ns / 1ps

module Processor_TB;

    // Inputs
    reg clk;
    reg reset;
    reg [2:0] SW;

    // Outputs
    wire [6:0] HEX0;

    // Instantiate the Unit Under Test (UUT)
    Processor uut (
        .clk(clk),
        .reset(reset),
        .SW(SW),
        .HEX0(HEX0)
    );

    // Clock generation
    initial begin
        clk = 0;
        forever #5 clk = ~clk;
    end

    // Test procedure
    initial begin
        // Initialize Inputs
        reset = 1;
        SW = 0;
        
        // Reset the processor
        #20;
        reset = 0;
        
        // Test ADD operation (r1 = r2 + r3)
        SW = 3'b001; // Select r1
        #100;
        
        // Test LOAD operation
        SW = 3'b000; // Select r0
        #100;
        
        // Test BEQ operation
        SW = 3'b010; // Select r2
        #100;
        
        // Test JMP operation
        SW = 3'b000; // Back to r0
        #100;
        
        $display("All tests completed");
        $finish;
    end
    
    // Dump waveforms
    initial begin
        $dumpfile("processor_tb.vcd");
        $dumpvars(0, Processor_TB);
    end

endmodule

processor_tb.vcd
$date
	Wed May 28 22:10:25 2025
$end
$version
	Icarus Verilog
$end
$timescale
	1ps
$end
$scope module Processor_TB $end
$var wire 7 ! HEX0 [6:0] $end
$var reg 3 " SW [2:0] $end
$var reg 1 # clk $end
$var reg 1 $ reset $end
$scope module uut $end
$var wire 3 % SW [2:0] $end
$var wire 1 # clk $end
$var wire 16 & reg_out [15:0] $end
$var wire 1 $ reset $end
$var wire 1 ' zero $end
$var wire 1 ( regwrite $end
$var wire 4 ) opcode [3:0] $end
$var wire 1 * memwrite $end
$var wire 1 + memtoreg $end
$var wire 1 , memread $end
$var wire 1 - jump $end
$var wire 1 . branch $end
$var wire 1 / alusrc $end
$var wire 3 0 aluop [2:0] $end
$var wire 7 1 HEX0 [6:0] $end
$scope module control $end
$var wire 1 # clk $end
$var wire 1 $ reset $end
$var wire 1 ' zero $end
$var wire 4 2 opcode [3:0] $end
$var parameter 3 3 ALU_ADD $end
$var parameter 3 4 ALU_AND $end
$var parameter 3 5 ALU_OR $end
$var parameter 3 6 ALU_PASS $end
$var parameter 3 7 ALU_SUB $end
$var parameter 3 8 BRANCH $end
$var parameter 3 9 DECODE $end
$var parameter 3 : EXECUTE $end
$var parameter 3 ; IFETCH $end
$var parameter 3 < JUMP $end
$var parameter 3 = MEM $end
$var parameter 4 > OP_ADD $end
$var parameter 4 ? OP_AND $end
$var parameter 4 @ OP_BEQ $end
$var parameter 4 A OP_JMP $end
$var parameter 4 B OP_LOAD $end
$var parameter 4 C OP_MOV $end
$var parameter 4 D OP_OR $end
$var parameter 4 E OP_STORE $end
$var parameter 4 F OP_SUB $end
$var parameter 3 G WB $end
$var reg 3 H aluop [2:0] $end
$var reg 1 / alusrc $end
$var reg 1 . branch $end
$var reg 3 I current_state [2:0] $end
$var reg 1 - jump $end
$var reg 1 , memread $end
$var reg 1 + memtoreg $end
$var reg 1 * memwrite $end
$var reg 3 J next_state [2:0] $end
$var reg 1 ( regwrite $end
$upscope $end
$scope module datapath $end
$var wire 3 K aluop [2:0] $end
$var wire 1 / alusrc $end
$var wire 1 . branch $end
$var wire 1 # clk $end
$var wire 16 L data_in [15:0] $end
$var wire 16 M instruction [15:0] $end
$var wire 1 - jump $end
$var wire 1 , memread $end
$var wire 1 + memtoreg $end
$var wire 1 * memwrite $end
$var wire 16 N reg_out [15:0] $end
$var wire 3 O reg_select [2:0] $end
$var wire 1 ( regwrite $end
$var wire 1 $ reset $end
$var wire 1 ' zero $end
$var wire 3 P rt [2:0] $end
$var wire 3 Q rs [2:0] $end
$var wire 3 R rd [2:0] $end
$var wire 4 S opcode [3:0] $end
$var reg 8 T pc [7:0] $end
$upscope $end
$scope module display $end
$var wire 4 U in [3:0] $end
$var reg 7 V out [6:0] $end
$upscope $end
$upscope $end
$upscope $end
$enddefinitions $end
$comment Show the parameter values. $end
$dumpall
b100 G
b1 F
b1001 E
b11 D
b100 C
b1000 B
b1101 A
b1100 @
b10 ?
b0 >
b11 =
b110 <
b0 ;
b10 :
b1 9
b101 8
b1 7
b100 6
b11 5
b10 4
b0 3
$end
#0
$dumpvars
b1111111 V
bz U
b0 T
b0 S
b1 R
b10 Q
b11 P
b0 O
bz N
b10011001000 M
b0 L
b0 K
b1 J
b0 I
b0 H
b0 2
b1111111 1
b0 0
0/
0.
0-
0,
0+
0*
b0 )
0(
z'
bz &
b0 %
1$
0#
b0 "
b1111111 !
$end
#5000
1#
#10000
0#
#15000
1#
#20000
0#
b1 "
b1 %
b1 O
0$
#25000
b1000 )
b1000 2
b1000 S
b0 Q
b1 P
b0 R
b11 J
b1000000001000000 M
b1 T
b1 I
1#
#30000
0#
#35000
1/
b100 J
bx )
bx 2
bx S
bx Q
bx P
bx R
b11 I
bx M
b10 T
1#
#40000
0#
#45000
0/
b0 J
b11 T
b100 I
1#
#50000
0#
#55000
b1 J
b0 I
b100 T
1#
#60000
0#
#65000
b0 J
b101 T
b1 I
1#
#70000
0#
#75000
b1 J
b0 I
b110 T
1#
#80000
0#
#85000
b0 J
b111 T
b1 I
1#
#90000
0#
#95000
b1 J
b0 I
b1000 T
1#
#100000
0#
#105000
b0 J
b1001 T
b1 I
1#
#110000
0#
#115000
b1 J
b0 I
b1010 T
1#
#120000
0#
b0 "
b0 %
b0 O
#125000
b0 J
b1011 T
b1 I
1#
#130000
0#
#135000
b1 J
b0 I
b1100 T
1#
#140000
0#
#145000
b0 J
b1101 T
b1 I
1#
#150000
0#
#155000
b1 J
b0 I
b1110 T
1#
#160000
0#
#165000
b0 J
b1111 T
b1 I
1#
#170000
0#
#175000
b1 J
b0 I
b10000 T
1#
#180000
0#
#185000
b0 J
b10001 T
b1 I
1#
#190000
0#
#195000
b1 J
b0 I
b10010 T
1#
#200000
0#
#205000
b0 J
b10011 T
b1 I
1#
#210000
0#
#215000
b1 J
b0 I
b10100 T
1#
#220000
0#
b10 "
b10 %
b10 O
#225000
b0 J
b10101 T
b1 I
1#
#230000
0#
#235000
b1 J
b0 I
b10110 T
1#
#240000
0#
#245000
b0 J
b10111 T
b1 I
1#
#250000
0#
#255000
b1 J
b0 I
b11000 T
1#
#260000
0#
#265000
b0 J
b11001 T
b1 I
1#
#270000
0#
#275000
b1 J
b0 I
b11010 T
1#
#280000
0#
#285000
b0 J
b11011 T
b1 I
1#
#290000
0#
#295000
b1 J
b0 I
b11100 T
1#
#300000
0#
#305000
b0 J
b11101 T
b1 I
1#
#310000
0#
#315000
b1 J
b0 I
b11110 T
1#
#320000
0#
b0 "
b0 %
b0 O
#325000
b0 J
b11111 T
b1 I
1#
#330000
0#
#335000
b1 J
b0 I
b100000 T
1#
#340000
0#
#345000
b0 J
b100001 T
b1 I
1#
#350000
0#
#355000
b1 J
b0 I
b100010 T
1#
#360000
0#
#365000
b0 J
b100011 T
b1 I
1#
#370000
0#
#375000
b1 J
b0 I
b100100 T
1#
#380000
0#
#385000
b0 J
b100101 T
b1 I
1#
#390000
0#
#395000
b1 J
b0 I
b100110 T
1#
#400000
0#
#405000
b0 J
b100111 T
b1 I
1#
#410000
0#
#415000
b1 J
b0 I
b101000 T
1#
